{"name":"stripe","qualifiedName":"stripe/stripe","comment":"","variables":{"required":{"name":"required","qualifiedName":"stripe/stripe.required","comment":"<p>See <a>stripe/stripe.Required</a></p>","final":false,"static":false,"constant":true,"type":[{"outer":"dynamic","inner":[]}],"annotations":[]}},"functions":{"setters":{},"getters":{},"constructors":{},"operators":{},"methods":{}},"classes":{"class":[{"name":"SubscriptionCollection","qualifiedName":"stripe/stripe.SubscriptionCollection"},{"name":"SubscriptionCreation","qualifiedName":"stripe/stripe.SubscriptionCreation","preview":"<p><a href=\"https://stripe.com/docs/api/curl#create_subscription\">Creating a new subscription</a></p>"},{"name":"Subscription","qualifiedName":"stripe/stripe.Subscription","preview":"<p><a href=\"https://stripe.com/docs/api/curl#subscriptions\">Subscriptions</a></p>"},{"name":"Refund","qualifiedName":"stripe/stripe.Refund"},{"name":"Dispute","qualifiedName":"stripe/stripe.Dispute","preview":"<p><a href=\"https://stripe.com/docs/api/curl#disputes\">Disputes</a></p>"},{"name":"PlanCollection","qualifiedName":"stripe/stripe.PlanCollection"},{"name":"PlanCreation","qualifiedName":"stripe/stripe.PlanCreation","preview":"<p><a href=\"https://stripe.com/docs/api/curl#create_plan\">Creating plans</a></p>"},{"name":"Plan","qualifiedName":"stripe/stripe.Plan","preview":"<p><a href=\"https://stripe.com/docs/api/curl#plans\">Plans</a></p>"},{"name":"InvoiceLineItemCollection","qualifiedName":"stripe/stripe.InvoiceLineItemCollection"},{"name":"Period","qualifiedName":"stripe/stripe.Period"},{"name":"InvoiceLineItem","qualifiedName":"stripe/stripe.InvoiceLineItem","preview":"<p><a href=\"https://stripe.com/docs/api/curl#invoice_line_item_object\">The invoice<em>line</em>item object</a></p>"},{"name":"Invoice","qualifiedName":"stripe/stripe.Invoice","preview":"<p><a href=\"https://stripe.com/docs/api/curl#invoices\">Invoices</a></p>"},{"name":"Discount","qualifiedName":"stripe/stripe.Discount","preview":"<p><a href=\"https://stripe.com/docs/api/curl#discounts\">Discounts</a></p>"},{"name":"CardCollection","qualifiedName":"stripe/stripe.CardCollection"},{"name":"CustomerCollection","qualifiedName":"stripe/stripe.CustomerCollection"},{"name":"CustomerUpdate","qualifiedName":"stripe/stripe.CustomerUpdate","preview":"<p><a href=\"https://stripe.com/docs/api/curl#update_customer\">Updating a Customer</a></p>"},{"name":"CustomerCreation","qualifiedName":"stripe/stripe.CustomerCreation","preview":"<p><a href=\"https://stripe.com/docs/api/curl#create_customer\">Creating a New Customer</a></p>"},{"name":"Customer","qualifiedName":"stripe/stripe.Customer","preview":"<p><a href=\"https://stripe.com/docs/api/curl#customers\">Customers</a></p>"},{"name":"CouponCollection","qualifiedName":"stripe/stripe.CouponCollection"},{"name":"CouponCreation","qualifiedName":"stripe/stripe.CouponCreation","preview":"<p><a href=\"https://stripe.com/docs/api/curl#create_coupon\">Creating coupons</a></p>"},{"name":"Coupon","qualifiedName":"stripe/stripe.Coupon","preview":"<p><a href=\"https://stripe.com/docs/api/curl#coupons\">Coupons</a></p>"},{"name":"ChargeCollection","qualifiedName":"stripe/stripe.ChargeCollection"},{"name":"ChargeUpdate","qualifiedName":"stripe/stripe.ChargeUpdate","preview":"<p><a href=\"https://stripe.com/docs/api/curl#update_charge\">Updating a Charge</a></p>"},{"name":"ChargeCreation","qualifiedName":"stripe/stripe.ChargeCreation","preview":"<p><a href=\"https://stripe.com/docs/api/curl#create_charge\">Creating a new charge (charging a credit card)</a></p>"},{"name":"Charge","qualifiedName":"stripe/stripe.Charge","preview":"<p><a href=\"https://stripe.com/docs/api/curl#charges\">Charges</a></p>"},{"name":"CardUpdate","qualifiedName":"stripe/stripe.CardUpdate","preview":"<p><a href=\"https://stripe.com/docs/api/curl#update_card\">Updating a card</a></p>"},{"name":"CardCreationWithToken","qualifiedName":"stripe/stripe.CardCreationWithToken","preview":"<p><a href=\"https://stripe.com/docs/api/curl#create_card\">Creating a new card</a></p>"},{"name":"CardCreation","qualifiedName":"stripe/stripe.CardCreation","preview":"<p><a href=\"https://stripe.com/docs/api/curl#create_card\">Creating a new card</a></p>"},{"name":"Card","qualifiedName":"stripe/stripe.Card","preview":"<p><a href=\"https://stripe.com/docs/api/curl#cards\">Card</a></p>"},{"name":"Fund","qualifiedName":"stripe/stripe.Fund"},{"name":"Balance","qualifiedName":"stripe/stripe.Balance","preview":"<p><a href=\"https://stripe.com/docs/api/curl#balance\">Balance</a></p>"},{"name":"Account","qualifiedName":"stripe/stripe.Account","preview":"<p><a href=\"https://stripe.com/docs/api/curl#account\">Account</a></p>"},{"name":"ApiResource","qualifiedName":"stripe/stripe.ApiResource","preview":"<p>ApiResources are resources that can be created and sent to the Stripe REST Api.</p>"},{"name":"ResourceCollection","qualifiedName":"stripe/stripe.ResourceCollection","preview":"<p>An abstract collection class that helps retrieving multiple elements of the\nsame resource.</p>"},{"name":"ResourceRequest","qualifiedName":"stripe/stripe.ResourceRequest","preview":"<p>The base class for request resources (eg: <a>stripe/stripe.CustomerCreation</a>,\n<a>stripe/stripe.CustomerUpdate</a>, etc...)</p>"},{"name":"Resource","qualifiedName":"stripe/stripe.Resource","preview":"<p>All objects sent through the Stripe REST API are <a>stripe/stripe.Resource</a>s, but only\n<a>stripe/stripe.ApiResource</a>s can be created, deleted, etc...</p>"},{"name":"Required","qualifiedName":"stripe/stripe.Required","preview":"<p>Used whenever a field of a resource is required</p>"},{"name":"StripeService","qualifiedName":"stripe/stripe.StripeService","preview":"<p>The service to communicate with the REST stripe API.</p>"}],"typedef":{},"error":[{"name":"BadRequestException","qualifiedName":"stripe/stripe.BadRequestException","preview":"<p>Invalid request errors arise when your request has invalid parameters.</p>"},{"name":"ApiErrorException","qualifiedName":"stripe/stripe.ApiErrorException","preview":"<p>API errors cover any other type of problem (e.g. a temporary problem with\nStripe's servers) and should turn up only very infrequently.</p>"},{"name":"CardErrorException","qualifiedName":"stripe/stripe.CardErrorException","preview":"<p>Card errors are the most common type of error you should expect to handle.\nThey result when the user enters a card that can't be charged for some reason.</p>"},{"name":"InvalidRequestErrorException","qualifiedName":"stripe/stripe.InvalidRequestErrorException","preview":"<p>Invalid request errors arise when your request has invalid parameters.</p>"},{"name":"StripeApiException","qualifiedName":"stripe/stripe.StripeApiException","preview":"<p>Exceptions thrown by Stripe</p>"},{"name":"InvalidDataReceivedException","qualifiedName":"stripe/stripe.InvalidDataReceivedException"}]},"packageName":"stripe","packageIntro":"<h1>Stripe Dart</h1>\n<p><a href=\"https://drone.io/github.com/enyo/stripe-dart/latest\">!<a href=\"https://drone.io/github.com/enyo/stripe-dart/status.png\">Build Status</a></a></p>\n<blockquote>\n<p>This library is not finished yet. <strong>Do not use.</strong>  \nIt will be ready to go in a few weeks.</p></blockquote>\n<p>Stripe API implemented in dart.</p>\n<p>Most of the model class documentations have been taken from the\n<a href=\"https://stripe.com/docs\">stripe documentation</a>.</p>\n<p>This implementation is based on the official Stripe Java and NodeJS API wrappers\nand written as a proper native dart library.</p>\n<h2>Usage</h2>\n<pre class=\"dart\"><code>import \"package:stripe/stripe.dart\";\n\nmain() {\n\n  StripeService.apiKey = \"sk_test_BQokikJOvBiI2HlWgH4olfQ2\";\n\n  var card = new CardCreation()\n      ..number = \"123123123\";\n\n  new CustomerCreation()\n      ..description = \"Customer for test@example.com\"\n      ..card = card\n      ..create()\n      .then((Customer customer) =&gt; print(customer))\n      .catchError((e) =&gt; handleError(e));\n\n}\n</code></pre>"}